artella/__init__.py
artella/dccs/__init__.py
artella/dccs/maya/__init__.py
artella/dccs/maya/__version__.py
artella/dccs/maya/_version.py
artella/dccs/maya/callback.py
artella/dccs/maya/dcc.py
artella/dccs/maya/downloader.py
artella/dccs/maya/mayapy_parser.py
artella/dccs/maya/parser.py
artella/dccs/maya/plugin.py
artella/dccs/maya/progress.py
artella/dccs/maya/utils.py
artella/dccs/maya/window.py
artella/dccs/maya/scripts/__init__.py
artella/dccs/maya/scripts/maya_parser.py
tests/__init__.py
tests/test_client.py
artella_dccs_maya-1.0.18.dist-info/METADATA
artella_dccs_maya-1.0.18.dist-info/WHEEL
artella_dccs_maya-1.0.18.dist-info/top_level.txt
artella_dccs_maya-1.0.18.dist-info/RECORD
