Metadata-Version: 2.1
Name: artella-dccs-maya
Version: 1.0.18
Summary: Artella plugin integration for Autodesk Maya.
Home-page: https://github.com/artella/artella-dccs-maya
Author: Artella, Inc
Author-email: support@artella.com
License: UNKNOWN
Platform: UNKNOWN
Requires-Dist: artella-plugins-core
Provides-Extra: dev
Requires-Dist: wheel ; extra == 'dev'
Provides-Extra: test
Requires-Dist: pytest ; extra == 'test'
